{
    "1601509571887903:6345868": {
        "RenderOrderComponent": true
    },
    "1601509571905737:6346128": {
        "InspectorComponent": {
            "Component.ScreenTransform": {
                "basicModeSetup": {
                    "attachBottom": "true",
                    "attachLeft": "true",
                    "attachRight": "false",
                    "attachTop": "false",
                    "fixHeight": "true",
                    "fixWidth": "true"
                },
                "isBasicMode": "false"
            }
        }
    }
}
