{
    "1602112467832982:814156": {
        "RenderOrderComponent": true
    },
    "1602112467853843:814420": {
        "InspectorComponent": {
            "Component.ScreenTransform": {
                "basicModeSetup": {
                    "attachBottom": "true",
                    "attachLeft": "false",
                    "attachRight": "false",
                    "attachTop": "false",
                    "fixHeight": "true",
                    "fixWidth": "true"
                },
                "isBasicMode": "true"
            }
        }
    }
}
